ce_scraper/__init__.py
ce_scraper/search_courses.py
ce_scraper-0.0.2.dist-info/LICENSE
ce_scraper-0.0.2.dist-info/METADATA
ce_scraper-0.0.2.dist-info/WHEEL
ce_scraper-0.0.2.dist-info/top_level.txt
ce_scraper-0.0.2.dist-info/RECORD
