Metadata-Version: 2.1
Name: ce-scraper
Version: 0.0.2
Summary: A simple python library for scraping some data from coursera
Home-page: UNKNOWN
Author: Kelem Negasi
Author-email: kellemnegasi@gmail.com
License: UNKNOWN
Platform: UNKNOWN
Classifier: Programming Language :: Python :: 3
Classifier: License :: OSI Approved :: MIT License
Classifier: Operating System :: OS Independent
Requires-Python: >=3.6
